animl/__init__.py
animl/__main__.py
animl/classification.py
animl/detection.py
animl/export.py
animl/file_management.py
animl/generator.py
animl/pipeline.py
animl/split.py
animl/video_processing.py
animl/reid/__init__.py
animl/reid/distance.py
animl/reid/inference.py
animl/utils/__init__.py
animl/utils/general.py
animl/utils/visualization.py
animl_lite-3.1.0.dist-info/licenses/LICENSE
animl_lite-3.1.0.dist-info/METADATA
animl_lite-3.1.0.dist-info/WHEEL
animl_lite-3.1.0.dist-info/top_level.txt
animl_lite-3.1.0.dist-info/RECORD
