Metadata-Version: 2.4
Name: animl-lite
Version: 3.1.0
Summary: Tools for classifying camera trap images
Author-email: Kyra Swanson <tswanson@sdzwa.org>
Project-URL: Homepage, https://github.com/conservationtechlab/animl-py
Keywords: camera trap,ecology,conservation,zoo,SDZWA,conservationtechlab
Requires-Python: >=3.12
License-File: LICENSE
Requires-Dist: numpy>=2.0.2
Requires-Dist: onnxruntime-gpu>=1.23.2
Requires-Dist: pandas>=2.2.2
Requires-Dist: pillow>=11.0.0
Requires-Dist: pyyaml>=6.0.3
Requires-Dist: opencv-python>=4.12.0.88
Requires-Dist: tqdm>=4.66.5
Dynamic: license-file
